trelloschedulercli/__init__.py
trelloschedulercli/__main__.py
trelloschedulercli/trellobot/trellobot.py
trelloschedulercli/trellobot/exceptions/environmentvarsnotsetexception.py
trelloschedulercli/trellobot/fparser/daystringutils.py
trelloschedulercli/trellobot/system/environment.py
trelloschedulercli/trellobot/system/jsonloader.py
trelloschedulercli/trellobot/system/terminal.py
trelloscheduler_cli-1.0.12.dist-info/LICENSE
trelloscheduler_cli-1.0.12.dist-info/METADATA
trelloscheduler_cli-1.0.12.dist-info/WHEEL
trelloscheduler_cli-1.0.12.dist-info/entry_points.txt
trelloscheduler_cli-1.0.12.dist-info/top_level.txt
trelloscheduler_cli-1.0.12.dist-info/RECORD
