Metadata-Version: 2.1
Name: trelloscheduler-cli
Version: 1.0.12
Summary: Create a Trello schedule through a commandline interface
Author-email: Olin Gallet <olindgallet@olingallet.com>
License: Apache License
Keywords: trello,cli,scheduler
Classifier: Programming Language :: Python
Classifier: Programming Language :: Python :: 3
License-File: LICENSE
Requires-Dist: certifi (==2022.12.7)
Requires-Dist: charset-normalizer (==2.1.1)
Requires-Dist: idna (==3.4)
Requires-Dist: oauthlib (==3.2.2)
Requires-Dist: plumbum (==1.8.0)
Requires-Dist: py-trello (==0.18.0)
Requires-Dist: python-dateutil (==2.8.2)
Requires-Dist: pytz (==2022.6)
Requires-Dist: requests (==2.28.1)
Requires-Dist: requests-oauthlib (==1.3.1)
Requires-Dist: six (==1.16.0)
Requires-Dist: urllib3 (==1.26.13)
